{
  "generated_at": "2026-07-19T14:22:59.675038+00:00",
  "week_ending": "2026-07-19",
  "summary": "David, what a week you've had! You've now lost 64.1 pounds from your starting weight of 315\u2014that's a massive achievement that speaks to your commitment. Your steady loss of 1.2 pounds per week shows you're in a sustainable rhythm, and hitting 250.9 pounds means you're well into new territory. I noticed you logged 11 days this period, which is solid, but let's aim to capture all seven days next week so we can spot any patterns that might help fine-tune things even more. You're doing the hard work consistently, and that consistency is exactly what creates lasting change. Keep going.",
  "stats": {
    "days_with_readings": 11,
    "latest_weight": 250.9,
    "total_lost_from_start": 64.1,
    "change_last_14d": -2.4,
    "rate_lbs_per_week": 1.2,
    "avg_weight": 252.7
  }
}